ararpy/Example - Check arr.py
ararpy/Example - Granite Cooling History.py
ararpy/Example - Plot temperature calibration.py
ararpy/Example - Show MDD results.py
ararpy/Example - Show all Kfs age spectra.py
ararpy/Example - Show random walk results.py
ararpy/Example - Tc calculation.py
ararpy/__init__.py
ararpy/test.py
ararpy/calc/__init__.py
ararpy/calc/age.py
ararpy/calc/arr.py
ararpy/calc/basic.py
ararpy/calc/corr.py
ararpy/calc/err.py
ararpy/calc/histogram.py
ararpy/calc/isochron.py
ararpy/calc/jvalue.py
ararpy/calc/plot.py
ararpy/calc/raw_funcs.py
ararpy/calc/regression.py
ararpy/calc/spectra.py
ararpy/examples/022_VU124-M11a.ahd
ararpy/examples/20WHA0103.age
ararpy/examples/22WHA0078.xls
ararpy/examples/22WHA0433.age
ararpy/examples/22WHA0433.arr
ararpy/examples/22WHA0433.full.xls
ararpy/examples/24WHN0001-51-592.XLS
ararpy/examples/AHD.input-filter
ararpy/examples/ArAr.calc
ararpy/examples/ArArCALC.age
ararpy/examples/NGX-600 - Copy.TXT
ararpy/examples/NGX-600.TXT
ararpy/examples/NGX-XLS.input-filter
ararpy/examples/Qtegra-exported-xls.input-filter
ararpy/examples/S01-239.csv
ararpy/examples/WH01.irra
ararpy/examples/WHA.pdf
ararpy/examples/raw_example.xls
ararpy/examples/sample-default.smp
ararpy/files/__init__.py
ararpy/files/arr_file.py
ararpy/files/basic.py
ararpy/files/calc_file.py
ararpy/files/new_file.py
ararpy/files/raw_file.py
ararpy/files/xls.py
ararpy/smp/EXPORT_TO_PDF_DATA_PROPERTIES.py
ararpy/smp/__init__.py
ararpy/smp/basic.py
ararpy/smp/calculation.py
ararpy/smp/consts.py
ararpy/smp/corr.py
ararpy/smp/diffusion_funcs.py
ararpy/smp/export.py
ararpy/smp/info.py
ararpy/smp/initial.py
ararpy/smp/json.py
ararpy/smp/plots.py
ararpy/smp/raw.py
ararpy/smp/sample.py
ararpy/smp/style.py
ararpy/smp/table.py
ararpy/thermo/__init__.py
ararpy/thermo/arrhenius.py
ararpy/thermo/atomic_level_random_walk.py
ararpy/thermo/basic.py
ararpy-0.2.5.dist-info/licenses/LICENSE
ararpy-0.2.5.dist-info/METADATA
ararpy-0.2.5.dist-info/WHEEL
ararpy-0.2.5.dist-info/top_level.txt
ararpy-0.2.5.dist-info/RECORD
