Metadata-Version: 2.4
Name: ararpy
Version: 0.2.5
Summary: A project for Ar-Ar geochronology
Home-page: https://github.com/wuyangchn/ararpy.git
Author: Yang Wu
Author-email: wuycug@hotmail.com
License: MIT
Classifier: Development Status :: 3 - Alpha
Classifier: Programming Language :: Python :: 3
Classifier: Operating System :: OS Independent
Requires-Python: >=3.5
License-File: LICENSE
Requires-Dist: chardet
Requires-Dist: numpy
Requires-Dist: pandas
Requires-Dist: parse
Requires-Dist: scipy
Requires-Dist: xlrd
Requires-Dist: XlsxWriter
Requires-Dist: pdf_maker
Dynamic: author
Dynamic: author-email
Dynamic: classifier
Dynamic: description
Dynamic: description-content-type
Dynamic: home-page
Dynamic: license
Dynamic: license-file
Dynamic: requires-dist
Dynamic: requires-python
Dynamic: summary
